{
  "consecutive_failures": 0,
  "current_state": "dry_run",
  "cycle": 206,
  "dry_run_plan": [
    [
      "git",
      "fetch",
      "origin"
    ],
    [
      "git",
      "status",
      "--short"
    ],
    [
      "bash",
      "scripts/run_experiment_cycle.sh",
      "--mode",
      "debug"
    ]
  ],
  "improvement_failures": 0,
  "last_commit_hash": "4d99b98f93d57d3128abd55972b1fe97e9a5739a",
  "last_commit_result": {
    "committed": true,
    "pushed": true
  },
  "last_cycle_timestamp": "20260516_210323",
  "last_status": "dry_run_planned",
  "oom_count": 0
}
